reflex_supporter/__init__.py
reflex_supporter/components/__init__.py
reflex_supporter/components/color_picker.py
reflex_supporter/components/json_editor.py
reflex_supporter/components/jumo_button.py
reflex_supporter/components/webcam.py
reflex_supporter-0.0.7.dist-info/METADATA
reflex_supporter-0.0.7.dist-info/WHEEL
reflex_supporter-0.0.7.dist-info/top_level.txt
reflex_supporter-0.0.7.dist-info/RECORD
