Metadata-Version: 2.1
Name: reflex-supporter
Version: 0.0.7
Summary: Reflex supporter
Home-page: https://github.com/automatethem/reflex-supporter
Author: Sang Ki Kwon
Author-email: automatethem@gmail.com
License: MIT
Requires-Dist: reflex
